{"name":"t0-c2-unordered","sources":[{"type":"kafka","topic":"aeon-source","partitions":[],"config":{"brokers":"redpanda.redpanda.svc.cluster.local:9092","group.id":"aeon-c2-unordered"}}],"processor":{"name":"__identity","version":"0.0.0"},"sinks":[{"type":"kafka","topic":"aeon-sink","config":{"brokers":"redpanda.redpanda.svc.cluster.local:9092","acks":"all","linger.ms":"5","batch.size":"131072","strategy":"unordered_batch"}}],"state":"created","created_at":0,"updated_at":0,"durability":{"mode":"unordered_batch"}}
